README.md
pyproject.toml
setup.cfg
setup.py
jschon_sort.egg-info/PKG-INFO
jschon_sort.egg-info/SOURCES.txt
jschon_sort.egg-info/dependency_links.txt
jschon_sort.egg-info/entry_points.txt
jschon_sort.egg-info/requires.txt
jschon_sort.egg-info/top_level.txt
jschon_tools/__init__.py
jschon_tools/_main.py
jschon_tools/_yaml.py
jschon_tools/cli.py