Metadata-Version: 2.1
Name: jschon-sort
Version: 0.1.0
Summary: Sorts a JSON or YAML document to match a JSON Schema's order of properties
Home-page: https://www.github.com/ikonst/jschon-sort
Maintainer: Ilya Konstantinov
Maintainer-email: ilya.konstantinov@gmail.com
License: UNKNOWN
Platform: UNKNOWN
Classifier: Programming Language :: Python :: 3
Requires-Python: >=3.8
